<?xml version="1.0" encoding="UTF-8"?>
<NFSe xmlns="http://www.sped.fazenda.gov.br/nfse"
      xmlns:ns2="http://www.w3.org/2000/09/xmldsig#"
      versao="1.01">
	<infNFSe Id="${ID_NFSE}">
		<xLocEmi>${CIDADE}</xLocEmi>
		<xLocPrestacao>${CIDADE}</xLocPrestacao>
		<nNFSe>${NUMERO_NFSE}</nNFSe>
		<cLocIncid>${CODIGO_MUNICIPIO}</cLocIncid>
		<xLocIncid>${CIDADE}</xLocIncid>
		<xTribNac>${DESCRICAO_SERVICO}</xTribNac>
		<verAplic>1.02</verAplic>
		<ambGer>1</ambGer>
		<tpEmis>1</tpEmis>
		<cStat>100</cStat>
		<dhProc>${DATA_HORA_PROCESSO}</dhProc>
		<nDFSe>${NUMERO_NFSE}</nDFSe>
		<emit>
			<CNPJ>${CNPJ_PRESTADOR}</CNPJ>
			<IM>${IM_PRESTADOR}</IM>
			<xNome>${NOME_PRESTADOR}</xNome>
			<xFant>${FANTASIA_PRESTADOR}</xFant>
			<enderNac>
				<xLgr>${LOGRADOURO_PREST}</xLgr>
				<nro>${NUMERO_PREST}</nro>
				<xCpl>${COMPLEMENTO_PREST}</xCpl>
				<xBairro>${BAIRRO_PREST}</xBairro>
				<cMun>${CODIGO_MUNICIPIO}</cMun>
				<UF>${UF}</UF>
				<CEP>${CEP}</CEP>
			</enderNac>
			<fone>${FONE}</fone>
			<email>${EMAIL}</email>
		</emit>
		<IBSCBS>
			<valores>
				<vBC>${VALOR_SERVICO}</vBC>
				<mun>
					<pIBSMun>${P_IBS_MUN}</pIBSMun>
				</mun>
				<uf>
					<pIBSUF>${P_IBS_UF}</pIBSUF>
				</uf>
				<fed>
					<pCBS>${P_CBS}</pCBS>
				</fed>
			</valores>
			<totCIBS>
				<gIBS>
					<vIBSTot>${V_IBS_TOTAL}</vIBSTot>
					<gIBSUFTot>
						<vIBSUF>${V_IBS_UF}</vIBSUF>
					</gIBSUFTot>
					<gIBSMunTot>
						<vIBSMun>${V_IBS_MUN}</vIBSMun>
					</gIBSMunTot>
				</gIBS>
				<gCBS>
					<vCBS>${V_CBS}</vCBS>
				</gCBS>
			</totCIBS>
		</IBSCBS>
		<valores>
			<vBC>${VALOR_SERVICO}</vBC>
			<pAliqAplic>${ALIQUOTA_ISS}</pAliqAplic>
			<issqn>
				<vISSQN>${VALOR_ISS}</vISSQN>
			</issqn>
			<vTotalRet>${VALOR_ISS}</vTotalRet>
			<vLiq>${VALOR_LIQ}</vLiq>
			<xOutInf>Chave de acesso no Ambiente Nacional: ${CHAVE_ACESSO}</xOutInf>
		</valores>
		<DPS versao="1.01">
			<infDPS Id="${ID_DPS}">
				<tpAmb>1</tpAmb>
				<dhEmi>${DATA_HORA_EMISSAO}</dhEmi>
				<verAplic>1.02</verAplic>
				<serie>${SERIE}</serie>
				<nDPS>${NUMERO_DPS}</nDPS>
				<dCompet>${DATA_COMPETENCIA}</dCompet>
				<tpEmit>1</tpEmit>
				<cLocEmi>${CODIGO_MUNICIPIO}</cLocEmi>
				<prest>
					<CNPJ>${CNPJ_PRESTADOR}</CNPJ>
					<IM>${IM_PRESTADOR}</IM>
					<xNome>${NOME_PRESTADOR}</xNome>
					<end>
						<endNac>
							<cMun>${CODIGO_MUNICIPIO}</cMun>
							<CEP>${CEP}</CEP>
						</endNac>
						<xLgr>${LOGRADOURO_PREST}</xLgr>
						<nro>${NUMERO_PREST}</nro>
						<xCpl>${COMPLEMENTO_PREST}</xCpl>
						<xBairro>${BAIRRO_PREST}</xBairro>
					</end>
					<fone>${FONE}</fone>
					<email>${EMAIL}</email>
					<regTrib>
						<opSimpNac>2</opSimpNac>
						<regEspTrib>0</regEspTrib>
					</regTrib>
				</prest>
				<toma>
					<CNPJ>${CNPJ_TOMADOR}</CNPJ>
					<xNome>${NOME_TOMADOR}</xNome>
					<end>
						<endNac>
							<cMun>${CODIGO_MUNICIPIO}</cMun>
							<CEP>${CEP}</CEP>
						</endNac>
						<xLgr>${LOGRADOURO_TOMA}</xLgr>
						<nro>${NUMERO_TOMA}</nro>
						<xCpl>${COMPLEMENTO_TOMA}</xCpl>
						<xBairro>${BAIRRO_TOMA}</xBairro>
					</end>
					<email>${EMAIL_TOMADOR}</email>
				</toma>
				<serv>
					<locPrest>
						<cLocPrestacao>${CODIGO_MUNICIPIO}</cLocPrestacao>
					</locPrest>
					<cServ>
						<cTribNac>${CODIGO_TRIB_NAC}</cTribNac>
						<cTribMun>${CODIGO_TRIB_MUN}</cTribMun>
						<xDescServ>${DESCRICAO_SERVICO}</xDescServ>
					</cServ>
					<infoCompl>
						<xInfComp>Nota gerada automaticamente para testes.</xInfComp>
					</infoCompl>
				</serv>
				<valores>
					<vServPrest>
						<vServ>${VALOR_SERVICO}</vServ>
					</vServPrest>
					<trib>
						<tribMun>
							<tribISSQN>1</tribISSQN>
							<vBC>${VALOR_SERVICO}</vBC>
							<pAliq>${ALIQUOTA_ISS}</pAliq>
							<tpRetISSQN>2</tpRetISSQN>
						</tribMun>
						<tribFed>
							<piscofins>
								<CST>01</CST>
								<vBCPisCofins>${VALOR_SERVICO}</vBCPisCofins>
								<pAliqPis>0.20</pAliqPis>
								<vPis>${VALOR_PIS}</vPis>
								<pAliqCofins>1.00</pAliqCofins>
								<vCofins>${VALOR_COFINS}</vCofins>
							</piscofins>
						</tribFed>
						<gIBSCBS>
							<CST>${CST_IBSCBS}</CST>
							<cClassTrib>${CLASSE_TRIB_IBSCBS}</cClassTrib>
						</gIBSCBS>
						<IBSCBS>
							<valores>
								<vBC>${VALOR_SERVICO}</vBC>
								<pIBSUF>${P_IBS_UF}</pIBSUF>
								<vIBSUF>${V_IBS_UF}</vIBSUF>
								<pIBSMun>${P_IBS_MUN}</pIBSMun>
								<vIBSMun>${V_IBS_MUN}</vIBSMun>
								<pCBS>${P_CBS}</pCBS>
								<vCBS>${V_CBS}</vCBS>
							</valores>
						</IBSCBS>
					</trib>
				</valores>
			</infDPS>
		</DPS>
		<chNota>${CHAVE_ACESSO}</chNota>
	</infNFSe>
	<Signature xmlns="http://www.w3.org/2000/09/xmldsig#">
		<SignedInfo>
			<CanonicalizationMethod Algorithm="http://www.w3.org/TR/2001/REC-xml-c14n-20010315"/>
			<SignatureMethod Algorithm="http://www.w3.org/2000/09/xmldsig#rsa-sha1"/>
			<Reference URI="#${ID_NFSE}">
				<Transforms>
					<Transform Algorithm="http://www.w3.org/2000/09/xmldsig#enveloped-signature"/>
					<Transform Algorithm="http://www.w3.org/TR/2001/REC-xml-c14n-20010315"/>
				</Transforms>
				<DigestMethod Algorithm="http://www.w3.org/2000/09/xmldsig#sha1"/>
				<DigestValue>VALOR_FAKE==</DigestValue>
			</Reference>
		</SignedInfo>
		<SignatureValue>ASSINATURA_FAKE==</SignatureValue>
		<KeyInfo>
			<X509Data>
				<X509Certificate>CERTIFICADO_FAKE==</X509Certificate>
			</X509Data>
		</KeyInfo>
	</Signature>
</NFSe>
